feijoa/__init__.py
feijoa/exceptions.py
feijoa/importance/__init__.py
feijoa/importance/evaluator.py
feijoa/importance/functional_anova.py
feijoa/importance/mdi.py
feijoa/importance/pca.py
feijoa/importance/rsfanova_boosted.py
feijoa/jobs/__init__.py
feijoa/jobs/job.py
feijoa/models/__init__.py
feijoa/models/configuration.py
feijoa/models/experiment.py
feijoa/models/result.py
feijoa/plugins/__init__.py
feijoa/plugins/plugin.py
feijoa/plugins/reducer.py
feijoa/search/__init__.py
feijoa/search/parameters.py
feijoa/search/seed.py
feijoa/search/space.py
feijoa/search/visitors.py
feijoa/search/oracles/__init__.py
feijoa/search/oracles/bayesian.py
feijoa/search/oracles/bcmaes.py
feijoa/search/oracles/finder.py
feijoa/search/oracles/genetic.py
feijoa/search/oracles/grid.py
feijoa/search/oracles/oracle.py
feijoa/search/oracles/pattern.py
feijoa/search/oracles/randomized.py
feijoa/search/oracles/meta/__init__.py
feijoa/search/oracles/meta/bandit.py
feijoa/search/oracles/meta/meta.py
feijoa/search/oracles/meta/roundrobin.py
feijoa/storages/__init__.py
feijoa/storages/storage.py
feijoa/storages/tiny.py
feijoa/storages/rdb/__init__.py
feijoa/storages/rdb/models.py
feijoa/storages/rdb/storage.py
feijoa/utils/__init__.py
feijoa/utils/imports.py
feijoa/utils/logging.py
feijoa/utils/misc.py
feijoa/utils/mixins.py
feijoa/utils/transformers.py
feijoa/utils/_oracle_parser/__init__.py
feijoa/utils/_oracle_parser/parser.py
feijoa/utils/_oracle_parser/parsetab.py
feijoa/visualization/__init__.py
feijoa/visualization/edf.py
feijoa/visualization/evaluations.py
feijoa/visualization/hist.py
feijoa/visualization/importances.py
feijoa/visualization/optimization_history.py
feijoa/visualization/parallel_coordinates.py
feijoa-0.1.11.dist-info/LICENSE
feijoa-0.1.11.dist-info/METADATA
feijoa-0.1.11.dist-info/WHEEL
feijoa-0.1.11.dist-info/top_level.txt
feijoa-0.1.11.dist-info/RECORD
