Metadata-Version: 2.1
Name: feijoa
Version: 0.1.11
Summary: Hyperparameter's optimization framework
Author-email: Konstantin Templin <1qnbhd@gmail.com>
Maintainer-email: Konstantin Templin <1qnbhd@gmail.com>
License: MIT
Project-URL: Repository, https://github.com/qnbhd/feijoa
Keywords: hyperparameters,BBO,optimization,autotuning
Classifier: Intended Audience :: Science/Research
Classifier: Intended Audience :: Developers
Classifier: Programming Language :: Python :: 3
Classifier: Programming Language :: Python :: 3.6
Classifier: Programming Language :: Python :: 3.7
Classifier: Programming Language :: Python :: 3.8
Classifier: Programming Language :: Python :: 3.9
Classifier: Programming Language :: Python :: 3.10
Classifier: Programming Language :: Python :: 3 :: Only
Classifier: Topic :: Scientific/Engineering
Classifier: Topic :: Scientific/Engineering :: Mathematics
Classifier: Topic :: Scientific/Engineering :: Artificial Intelligence
Classifier: Topic :: Software Development
Classifier: Topic :: Software Development :: Libraries
Classifier: Topic :: Software Development :: Libraries :: Python Modules
Requires-Python: >=3.7
License-File: LICENSE
Requires-Dist: numpy (>=1.19.5)
Requires-Dist: pandas (>=0.25.3)
Requires-Dist: rich (>=10.11.0)
Requires-Dist: pydantic (>=1.7.4)
Requires-Dist: mabalgs (>=0.6.8)
Requires-Dist: plotly (>=5.9.0)
Requires-Dist: PyYAML (>=6.0)
Requires-Dist: scikit-learn (>=0.24.2)
Requires-Dist: joblib (>=1.1.0)
Requires-Dist: SQLAlchemy (>=1.4.39)
Requires-Dist: ply (>=3.11)
Provides-Extra: all
Requires-Dist: click (>=8.0.4) ; extra == 'all'
Requires-Dist: numba (>=0.53.1) ; extra == 'all'
Requires-Dist: tinydb (>=4.7.0) ; extra == 'all'
Requires-Dist: executor (>=23.2) ; extra == 'all'
Requires-Dist: scikit-optimize (>=0.9.0) ; extra == 'all'
Provides-Extra: dev
Requires-Dist: pytest (>=7.0.1) ; extra == 'dev'
Requires-Dist: isort (>=5.8.0) ; extra == 'dev'
Requires-Dist: flake8 (>=4.0.1) ; extra == 'dev'
Requires-Dist: pytest-cov (>=3.0.0) ; extra == 'dev'
Requires-Dist: importlib-metadata ; extra == 'dev'
